{"2026-05-01": {"calls": [{"strike": 100.0, "lastPrice": 92.0, "bid": 82.25, "ask": 85.7, "volume": 0.0}, {"strike": 115.0, "lastPrice": 80.4, "bid": 67.3, "ask": 70.45, "volume": 0.0}, {"strike": 160.0, "lastPrice": 27.2, "bid": 22.8, "ask": 25.5, "volume": 0.0}, {"strike": 165.0, "lastPrice": 27.37, "bid": 18.3, "ask": 20.65, "volume": 1.0}, {"strike": 170.0, "lastPrice": 14.13, "bid": 13.95, "ask": 15.75, "volume": 20.0}, {"strike": 172.5, "lastPrice": 14.72, "bid": 11.5, "ask": 13.5, "volume": 0.0}, {"strike": 175.0, "lastPrice": 10.43, "bid": 9.35, "ask": 11.45, "volume": 11.0}, {"strike": 177.5, "lastPrice": 7.8, "bid": 8.4, "ask": 9.4, "volume": 241.0}, {"strike": 180.0, "lastPrice": 7.0, "bid": 6.8, "ask": 7.55, "volume": 433.0}, {"strike": 182.5, "lastPrice": 5.65, "bid": 5.05, "ask": 6.25, "volume": 102.0}, {"strike": 185.0, "lastPrice": 4.2, "bid": 4.1, "ask": 4.3, "volume": 362.0}, {"strike": 187.5, "lastPrice": 3.05, "bid": 3.05, "ask": 3.4, "volume": 191.0}, {"strike": 190.0, "lastPrice": 2.34, "bid": 2.25, "ask": 2.42, "volume": 787.0}, {"strike": 192.5, "lastPrice": 1.75, "bid": 1.62, "ask": 1.75, "volume": 357.0}, {"strike": 195.0, "lastPrice": 1.25, "bid": 1.04, "ask": 1.3, "volume": 355.0}, {"strike": 197.5, "lastPrice": 0.87, "bid": 0.78, "ask": 1.02, "volume": 173.0}, {"strike": 200.0, "lastPrice": 0.83, "bid": 0.5, "ask": 0.72, "volume": 270.0}, {"strike": 202.5, "lastPrice": 0.45, "bid": 0.29, "ask": 0.6, "volume": 54.0}, {"strike": 205.0, "lastPrice": 0.43, "bid": 0.3, "ask": 0.43, "volume": 116.0}, {"strike": 207.5, "lastPrice": 0.66, "bid": 0.03, "ask": 0.87, "volume": 0.0}, {"strike": 210.0, "lastPrice": 0.25, "bid": 0.18, "ask": 0.4, "volume": 66.0}, {"strike": 215.0, "lastPrice": 0.17, "bid": 0.09, "ask": 0.41, "volume": 36.0}, {"strike": 220.0, "lastPrice": 0.07, "bid": 0.05, "ask": 0.29, "volume": 5.0}, {"strike": 225.0, "lastPrice": 0.04, "bid": 0.03, "ask": 0.14, "volume": 11.0}, {"strike": 230.0, "lastPrice": 0.08, "bid": 0.01, "ask": 0.38, "volume": 20.0}, {"strike": 235.0, "lastPrice": 0.09, "bid": 0.0, "ask": 0.27, "volume": 1.0}, {"strike": 240.0, "lastPrice": 0.01, "bid": 0.0, "ask": 1.44, "volume": 1.0}, {"strike": 245.0, "lastPrice": 0.21, "bid": 0.0, "ask": 0.35, "volume": 2.0}, {"strike": 250.0, "lastPrice": 0.07, "bid": 0.0, "ask": 1.0, "volume": 6.0}, {"strike": 255.0, "lastPrice": 1.06, "bid": 0.0, "ask": 2.15, "volume": 1.0}, {"strike": 260.0, "lastPrice": 1.5, "bid": 0.0, "ask": 2.14, "volume": 1.0}, {"strike": 265.0, "lastPrice": 0.64, "bid": 0.0, "ask": 2.14, "volume": 2.0}, {"strike": 270.0, "lastPrice": 1.16, "bid": 0.0, "ask": 1.2, "volume": 1.0}], "puts": [{"strike": 130.0, "lastPrice": 0.19, "bid": 0.01, "ask": 0.27, "volume": 6.0}, {"strike": 135.0, "lastPrice": 0.3, "bid": 0.0, "ask": 1.55, "volume": 0.0}, {"strike": 140.0, "lastPrice": 0.11, "bid": 0.0, "ask": 0.29, "volume": 4.0}, {"strike": 145.0, "lastPrice": 0.12, "bid": 0.0, "ask": 0.58, "volume": 7.0}, {"strike": 150.0, "lastPrice": 0.1, "bid": 0.0, "ask": 0.63, "volume": 28.0}, {"strike": 155.0, "lastPrice": 0.1, "bid": 0.0, "ask": 0.47, "volume": 5.0}, {"strike": 160.0, "lastPrice": 0.33, "bid": 0.2, "ask": 0.46, "volume": 5.0}, {"strike": 162.5, "lastPrice": 0.26, "bid": 0.09, "ask": 0.35, "volume": 5.0}, {"strike": 165.0, "lastPrice": 0.44, "bid": 0.28, "ask": 0.52, "volume": 54.0}, {"strike": 167.5, "lastPrice": 0.46, "bid": 0.31, "ask": 0.57, "volume": 58.0}, {"strike": 170.0, "lastPrice": 0.75, "bid": 0.59, "ask": 0.72, "volume": 205.0}, {"strike": 172.5, "lastPrice": 0.92, "bid": 0.76, "ask": 1.05, "volume": 22.0}, {"strike": 175.0, "lastPrice": 1.37, "bid": 1.24, "ask": 1.4, "volume": 288.0}, {"strike": 177.5, "lastPrice": 1.96, "bid": 1.79, "ask": 1.98, "volume": 79.0}, {"strike": 180.0, "lastPrice": 2.71, "bid": 2.54, "ask": 2.94, "volume": 256.0}, {"strike": 182.5, "lastPrice": 3.6, "bid": 3.5, "ask": 3.8, "volume": 177.0}, {"strike": 185.0, "lastPrice": 4.88, "bid": 4.65, "ask": 5.05, "volume": 91.0}, {"strike": 187.5, "lastPrice": 6.15, "bid": 6.1, "ask": 6.55, "volume": 16.0}, {"strike": 190.0, "lastPrice": 8.0, "bid": 7.55, "ask": 8.4, "volume": 25.0}, {"strike": 192.5, "lastPrice": 13.14, "bid": 9.45, "ask": 10.45, "volume": 1.0}, {"strike": 195.0, "lastPrice": 11.95, "bid": 10.95, "ask": 12.5, "volume": 286.0}, {"strike": 197.5, "lastPrice": 15.85, "bid": 13.55, "ask": 15.4, "volume": 1.0}, {"strike": 200.0, "lastPrice": 22.18, "bid": 15.8, "ask": 17.7, "volume": 1.0}, {"strike": 202.5, "lastPrice": 16.12, "bid": 17.6, "ask": 20.05, "volume": 0.0}, {"strike": 205.0, "lastPrice": 21.87, "bid": 20.0, "ask": 22.4, "volume": 2.0}, {"strike": 210.0, "lastPrice": 31.59, "bid": 24.95, "ask": 27.25, "volume": 1.0}, {"strike": 215.0, "lastPrice": 27.06, "bid": 29.65, "ask": 32.85, "volume": 1.0}, {"strike": 220.0, "lastPrice": 29.17, "bid": 34.9, "ask": 37.25, "volume": 28.0}, {"strike": 225.0, "lastPrice": 34.12, "bid": 39.95, "ask": 42.45, "volume": 27.0}, {"strike": 230.0, "lastPrice": 26.0, "bid": 44.85, "ask": 47.8, "volume": 1.0}, {"strike": 235.0, "lastPrice": 33.45, "bid": 50.1, "ask": 52.25, "volume": 3.0}, {"strike": 240.0, "lastPrice": 49.2, "bid": 54.85, "ask": 57.85, "volume": 1.0}]}, "2026-05-08": {"calls": [{"strike": 105.0, "lastPrice": 85.4, "bid": 77.35, "ask": 81.3, "volume": 1.0}, {"strike": 125.0, "lastPrice": 82.0, "bid": 57.35, "ask": 61.35, "volume": 0.0}, {"strike": 135.0, "lastPrice": 72.0, "bid": 47.45, "ask": 51.4, "volume": 0.0}, {"strike": 150.0, "lastPrice": 29.95, "bid": 32.65, "ask": 36.05, "volume": 1.0}, {"strike": 155.0, "lastPrice": 58.78, "bid": 27.75, "ask": 30.85, "volume": 0.0}, {"strike": 160.0, "lastPrice": 20.14, "bid": 23.1, "ask": 26.1, "volume": 1.0}, {"strike": 170.0, "lastPrice": 13.48, "bid": 14.1, "ask": 16.4, "volume": 46.0}, {"strike": 175.0, "lastPrice": 12.49, "bid": 11.1, "ask": 12.4, "volume": 1.0}, {"strike": 180.0, "lastPrice": 7.53, "bid": 7.4, "ask": 8.4, "volume": 117.0}, {"strike": 185.0, "lastPrice": 5.14, "bid": 4.95, "ask": 5.3, "volume": 362.0}, {"strike": 190.0, "lastPrice": 3.1, "bid": 3.0, "ask": 3.25, "volume": 482.0}, {"strike": 195.0, "lastPrice": 1.75, "bid": 1.7, "ask": 1.94, "volume": 101.0}, {"strike": 200.0, "lastPrice": 1.14, "bid": 1.0, "ask": 1.14, "volume": 126.0}, {"strike": 205.0, "lastPrice": 0.61, "bid": 0.44, "ask": 0.87, "volume": 17.0}, {"strike": 210.0, "lastPrice": 0.47, "bid": 0.37, "ask": 0.56, "volume": 879.0}, {"strike": 215.0, "lastPrice": 0.26, "bid": 0.0, "ask": 0.88, "volume": 44.0}, {"strike": 220.0, "lastPrice": 0.22, "bid": 0.0, "ask": 0.58, "volume": 2.0}, {"strike": 225.0, "lastPrice": 0.09, "bid": 0.0, "ask": 0.3, "volume": 2.0}, {"strike": 230.0, "lastPrice": 0.85, "bid": 0.01, "ask": 0.75, "volume": 173.0}, {"strike": 235.0, "lastPrice": 0.1, "bid": 0.01, "ask": 0.7, "volume": 3.0}, {"strike": 240.0, "lastPrice": 0.07, "bid": 0.0, "ask": 0.73, "volume": 2.0}, {"strike": 245.0, "lastPrice": 0.94, "bid": 0.0, "ask": 2.16, "volume": 2.0}, {"strike": 250.0, "lastPrice": 0.05, "bid": 0.0, "ask": 2.16, "volume": 4.0}], "puts": [{"strike": 120.0, "lastPrice": 0.11, "bid": 0.0, "ask": 2.14, "volume": 0.0}, {"strike": 140.0, "lastPrice": 0.09, "bid": 0.0, "ask": 0.13, "volume": 2.0}, {"strike": 145.0, "lastPrice": 0.25, "bid": 0.0, "ask": 2.23, "volume": 4.0}, {"strike": 150.0, "lastPrice": 0.18, "bid": 0.0, "ask": 0.23, "volume": 4.0}, {"strike": 155.0, "lastPrice": 0.26, "bid": 0.0, "ask": 0.33, "volume": 244.0}, {"strike": 160.0, "lastPrice": 0.32, "bid": 0.3, "ask": 0.48, "volume": 262.0}, {"strike": 165.0, "lastPrice": 0.63, "bid": 0.43, "ask": 0.73, "volume": 14.0}, {"strike": 170.0, "lastPrice": 1.03, "bid": 0.95, "ask": 1.12, "volume": 70.0}, {"strike": 175.0, "lastPrice": 1.89, "bid": 1.77, "ask": 2.15, "volume": 61.0}, {"strike": 180.0, "lastPrice": 3.5, "bid": 3.2, "ask": 3.55, "volume": 345.0}, {"strike": 185.0, "lastPrice": 5.56, "bid": 5.4, "ask": 5.8, "volume": 25.0}, {"strike": 190.0, "lastPrice": 12.16, "bid": 8.05, "ask": 9.05, "volume": 10.0}, {"strike": 195.0, "lastPrice": 16.45, "bid": 11.95, "ask": 12.7, "volume": 4.0}, {"strike": 200.0, "lastPrice": 18.15, "bid": 15.65, "ask": 18.0, "volume": 7.0}, {"strike": 205.0, "lastPrice": 21.76, "bid": 20.2, "ask": 23.15, "volume": 8.0}, {"strike": 210.0, "lastPrice": 28.22, "bid": 24.9, "ask": 28.0, "volume": 1.0}, {"strike": 215.0, "lastPrice": 10.26, "bid": 29.95, "ask": 32.9, "volume": 0.0}, {"strike": 220.0, "lastPrice": 35.88, "bid": 33.95, "ask": 37.9, "volume": 2.0}, {"strike": 225.0, "lastPrice": 33.5, "bid": 38.9, "ask": 42.85, "volume": 2.0}, {"strike": 240.0, "lastPrice": 36.5, "bid": 53.9, "ask": 57.85, "volume": 2.0}]}, "2026-05-15": {"calls": [{"strike": 100.0, "lastPrice": 83.96, "bid": 0.0, "ask": 0.0, "volume": 11}, {"strike": 110.0, "lastPrice": 90.31, "bid": 72.4, "ask": 76.35, "volume": 4}, {"strike": 115.0, "lastPrice": 85.29, "bid": 67.45, "ask": 71.4, "volume": 212}, {"strike": 120.0, "lastPrice": 80.63, "bid": 62.45, "ask": 66.4, "volume": 2}, {"strike": 125.0, "lastPrice": 60.96, "bid": 57.45, "ask": 61.45, "volume": 9}, {"strike": 130.0, "lastPrice": 52.0, "bid": 52.5, "ask": 56.4, "volume": 2}, {"strike": 135.0, "lastPrice": 63.09, "bid": 47.55, "ask": 51.45, "volume": 2}, {"strike": 140.0, "lastPrice": 53.33, "bid": 42.6, "ask": 46.5, "volume": 1}, {"strike": 145.0, "lastPrice": 41.17, "bid": 37.6, "ask": 41.6, "volume": 9}, {"strike": 150.0, "lastPrice": 32.97, "bid": 33.7, "ask": 36.05, "volume": 3}, {"strike": 155.0, "lastPrice": 25.0, "bid": 28.55, "ask": 31.05, "volume": 11}, {"strike": 160.0, "lastPrice": 24.33, "bid": 23.65, "ask": 26.25, "volume": 25}, {"strike": 165.0, "lastPrice": 20.39, "bid": 19.35, "ask": 21.45, "volume": 27}, {"strike": 170.0, "lastPrice": 15.85, "bid": 15.05, "ask": 16.5, "volume": 23}, {"strike": 175.0, "lastPrice": 11.84, "bid": 11.05, "ask": 12.2, "volume": 52}, {"strike": 180.0, "lastPrice": 8.55, "bid": 8.3, "ask": 8.85, "volume": 595}, {"strike": 185.0, "lastPrice": 5.75, "bid": 5.55, "ask": 5.75, "volume": 1680}, {"strike": 190.0, "lastPrice": 3.7, "bid": 3.5, "ask": 3.75, "volume": 3321}, {"strike": 195.0, "lastPrice": 2.27, "bid": 2.15, "ask": 2.27, "volume": 1970}, {"strike": 200.0, "lastPrice": 1.44, "bid": 1.33, "ask": 1.43, "volume": 2408}, {"strike": 210.0, "lastPrice": 0.52, "bid": 0.4, "ask": 0.65, "volume": 537}, {"strike": 220.0, "lastPrice": 0.27, "bid": 0.2, "ask": 0.36, "volume": 347}, {"strike": 230.0, "lastPrice": 0.11, "bid": 0.1, "ask": 0.18, "volume": 23}, {"strike": 240.0, "lastPrice": 0.2, "bid": 0.02, "ask": 0.22, "volume": 6}, {"strike": 250.0, "lastPrice": 0.08, "bid": 0.08, "ask": 0.14, "volume": 9}, {"strike": 260.0, "lastPrice": 0.12, "bid": 0.02, "ask": 0.33, "volume": 11}, {"strike": 270.0, "lastPrice": 0.15, "bid": 0.0, "ask": 0.5, "volume": 1}, {"strike": 280.0, "lastPrice": 0.1, "bid": 0.0, "ask": 0.54, "volume": 1}, {"strike": 290.0, "lastPrice": 0.18, "bid": 0.0, "ask": 0.32, "volume": 1}, {"strike": 300.0, "lastPrice": 0.14, "bid": 0.0, "ask": 0.49, "volume": 5}], "puts": [{"strike": 75.0, "lastPrice": 0.12, "bid": 0.0, "ask": 0.25, "volume": 3.0}, {"strike": 80.0, "lastPrice": 0.02, "bid": 0.0, "ask": 2.13, "volume": 1.0}, {"strike": 85.0, "lastPrice": 0.14, "bid": 0.0, "ask": 0.0, "volume": 1.0}, {"strike": 90.0, "lastPrice": 0.1, "bid": 0.0, "ask": 2.13, "volume": 5.0}, {"strike": 95.0, "lastPrice": 0.05, "bid": 0.0, "ask": 0.1, "volume": 2.0}, {"strike": 100.0, "lastPrice": 0.25, "bid": 0.0, "ask": 0.32, "volume": 5.0}, {"strike": 105.0, "lastPrice": 0.34, "bid": 0.0, "ask": 0.49, "volume": 9.0}, {"strike": 110.0, "lastPrice": 0.09, "bid": 0.0, "ask": 0.32, "volume": 2.0}, {"strike": 115.0, "lastPrice": 0.19, "bid": 0.0, "ask": 0.31, "volume": 1.0}, {"strike": 120.0, "lastPrice": 0.05, "bid": 0.05, "ask": 0.19, "volume": 2.0}, {"strike": 125.0, "lastPrice": 0.16, "bid": 0.0, "ask": 0.34, "volume": 10.0}, {"strike": 130.0, "lastPrice": 0.07, "bid": 0.05, "ask": 0.32, "volume": 8.0}, {"strike": 135.0, "lastPrice": 0.19, "bid": 0.0, "ask": 0.35, "volume": 102.0}, {"strike": 140.0, "lastPrice": 0.21, "bid": 0.0, "ask": 0.45, "volume": 7.0}, {"strike": 145.0, "lastPrice": 0.18, "bid": 0.05, "ask": 0.19, "volume": 8.0}, {"strike": 150.0, "lastPrice": 0.14, "bid": 0.14, "ask": 0.25, "volume": 160.0}, {"strike": 155.0, "lastPrice": 0.26, "bid": 0.05, "ask": 0.4, "volume": 331.0}, {"strike": 160.0, "lastPrice": 0.46, "bid": 0.33, "ask": 0.54, "volume": 792.0}, {"strike": 165.0, "lastPrice": 0.74, "bid": 0.75, "ask": 0.85, "volume": 222.0}, {"strike": 170.0, "lastPrice": 1.35, "bid": 1.27, "ask": 1.44, "volume": 1008.0}, {"strike": 175.0, "lastPrice": 2.34, "bid": 2.26, "ask": 2.44, "volume": 825.0}, {"strike": 180.0, "lastPrice": 3.94, "bid": 3.8, "ask": 4.05, "volume": 498.0}, {"strike": 185.0, "lastPrice": 6.12, "bid": 6.0, "ask": 6.35, "volume": 336.0}, {"strike": 190.0, "lastPrice": 9.05, "bid": 8.9, "ask": 9.35, "volume": 212.0}, {"strike": 195.0, "lastPrice": 12.83, "bid": 12.2, "ask": 13.5, "volume": 302.0}, {"strike": 200.0, "lastPrice": 16.79, "bid": 16.3, "ask": 17.3, "volume": 85.0}, {"strike": 210.0, "lastPrice": 29.74, "bid": 25.4, "ask": 27.3, "volume": 2.0}, {"strike": 220.0, "lastPrice": 32.5, "bid": 34.8, "ask": 37.95, "volume": 2.0}, {"strike": 230.0, "lastPrice": 26.7, "bid": 44.7, "ask": 47.85, "volume": 4.0}, {"strike": 240.0, "lastPrice": 49.3, "bid": 54.3, "ask": 57.85, "volume": 2.0}, {"strike": 250.0, "lastPrice": 47.5, "bid": 64.55, "ask": 67.85, "volume": 3.0}, {"strike": 260.0, "lastPrice": 47.5, "bid": 74.5, "ask": 77.85, "volume": 10.0}, {"strike": 270.0, "lastPrice": 68.39, "bid": 84.45, "ask": 87.85, "volume": 1.0}, {"strike": 280.0, "lastPrice": 75.65, "bid": 94.4, "ask": 98.0, "volume": 0.0}]}, "2026-06-18": {"calls": [{"strike": 70.0, "lastPrice": 117.99, "bid": 112.25, "ask": 116.2, "volume": 2.0}, {"strike": 75.0, "lastPrice": 108.6, "bid": 0.0, "ask": 0.0, "volume": 8.0}, {"strike": 80.0, "lastPrice": 103.55, "bid": 0.0, "ask": 0.0, "volume": 8.0}, {"strike": 85.0, "lastPrice": 61.42, "bid": 63.6, "ask": 68.45, "volume": 0.0}, {"strike": 90.0, "lastPrice": 108.45, "bid": 92.25, "ask": 96.3, "volume": 1.0}, {"strike": 95.0, "lastPrice": 88.5, "bid": 0.0, "ask": 0.0, "volume": 2.0}, {"strike": 100.0, "lastPrice": 100.42, "bid": 82.2, "ask": 86.3, "volume": 1.0}, {"strike": 105.0, "lastPrice": 79.9, "bid": 0.0, "ask": 0.0, "volume": 150.0}, {"strike": 110.0, "lastPrice": 80.4, "bid": 0.0, "ask": 0.0, "volume": 6.0}, {"strike": 115.0, "lastPrice": 96.89, "bid": 67.55, "ask": 71.45, "volume": 3.0}, {"strike": 120.0, "lastPrice": 70.63, "bid": 62.5, "ask": 66.45, "volume": 5.0}, {"strike": 125.0, "lastPrice": 75.9, "bid": 57.55, "ask": 61.5, "volume": 5.0}, {"strike": 130.0, "lastPrice": 80.2, "bid": 53.25, "ask": 56.5, "volume": 1.0}, {"strike": 135.0, "lastPrice": 48.05, "bid": 47.65, "ask": 51.55, "volume": 2.0}, {"strike": 140.0, "lastPrice": 46.0, "bid": 42.7, "ask": 46.65, "volume": 3.0}, {"strike": 145.0, "lastPrice": 46.45, "bid": 38.4, "ask": 40.65, "volume": 3.0}, {"strike": 150.0, "lastPrice": 30.0, "bid": 33.55, "ask": 35.55, "volume": 7.0}, {"strike": 155.0, "lastPrice": 24.51, "bid": 28.8, "ask": 30.75, "volume": 33.0}, {"strike": 160.0, "lastPrice": 25.25, "bid": 24.4, "ask": 26.3, "volume": 49.0}, {"strike": 165.0, "lastPrice": 20.88, "bid": 20.1, "ask": 21.65, "volume": 116.0}, {"strike": 170.0, "lastPrice": 16.7, "bid": 16.25, "ask": 17.85, "volume": 97.0}, {"strike": 175.0, "lastPrice": 12.75, "bid": 12.55, "ask": 13.85, "volume": 8.0}, {"strike": 180.0, "lastPrice": 10.06, "bid": 9.95, "ask": 10.2, "volume": 370.0}, {"strike": 185.0, "lastPrice": 7.75, "bid": 7.4, "ask": 7.7, "volume": 447.0}, {"strike": 190.0, "lastPrice": 5.5, "bid": 5.35, "ask": 5.6, "volume": 932.0}, {"strike": 195.0, "lastPrice": 3.9, "bid": 3.8, "ask": 4.1, "volume": 452.0}, {"strike": 200.0, "lastPrice": 2.81, "bid": 2.72, "ask": 2.87, "volume": 2210.0}, {"strike": 210.0, "lastPrice": 1.4, "bid": 1.27, "ask": 1.52, "volume": 469.0}, {"strike": 220.0, "lastPrice": 0.65, "bid": 0.66, "ask": 0.73, "volume": 675.0}, {"strike": 230.0, "lastPrice": 0.35, "bid": 0.3, "ask": 0.58, "volume": 321.0}, {"strike": 240.0, "lastPrice": 0.3, "bid": 0.17, "ask": 0.35, "volume": 127.0}, {"strike": 250.0, "lastPrice": 0.26, "bid": 0.11, "ask": 0.5, "volume": 1.0}, {"strike": 260.0, "lastPrice": 0.15, "bid": 0.01, "ask": 0.42, "volume": 1.0}, {"strike": 270.0, "lastPrice": 0.18, "bid": 0.0, "ask": 0.2, "volume": 2.0}], "puts": [{"strike": 70.0, "lastPrice": 0.05, "bid": 0.0, "ask": 0.05, "volume": 2}, {"strike": 75.0, "lastPrice": 0.05, "bid": 0.0, "ask": 0.08, "volume": 19}, {"strike": 80.0, "lastPrice": 0.02, "bid": 0.0, "ask": 2.14, "volume": 1}, {"strike": 85.0, "lastPrice": 0.01, "bid": 0.0, "ask": 0.25, "volume": 3}, {"strike": 90.0, "lastPrice": 0.05, "bid": 0.0, "ask": 0.05, "volume": 3}, {"strike": 95.0, "lastPrice": 0.05, "bid": 0.0, "ask": 0.67, "volume": 6}, {"strike": 100.0, "lastPrice": 0.15, "bid": 0.0, "ask": 2.18, "volume": 3}, {"strike": 105.0, "lastPrice": 0.17, "bid": 0.0, "ask": 0.37, "volume": 4}, {"strike": 110.0, "lastPrice": 0.09, "bid": 0.0, "ask": 0.38, "volume": 2}, {"strike": 115.0, "lastPrice": 0.11, "bid": 0.0, "ask": 0.42, "volume": 2}, {"strike": 120.0, "lastPrice": 0.11, "bid": 0.05, "ask": 0.24, "volume": 1}, {"strike": 125.0, "lastPrice": 0.15, "bid": 0.1, "ask": 0.3, "volume": 1}, {"strike": 130.0, "lastPrice": 0.19, "bid": 0.14, "ask": 0.26, "volume": 4}, {"strike": 135.0, "lastPrice": 0.25, "bid": 0.24, "ask": 0.67, "volume": 58}, {"strike": 140.0, "lastPrice": 0.37, "bid": 0.11, "ask": 0.46, "volume": 152}, {"strike": 145.0, "lastPrice": 0.47, "bid": 0.29, "ask": 0.59, "volume": 165}, {"strike": 150.0, "lastPrice": 0.65, "bid": 0.53, "ask": 0.77, "volume": 137}, {"strike": 155.0, "lastPrice": 0.98, "bid": 0.84, "ask": 1.09, "volume": 238}, {"strike": 160.0, "lastPrice": 1.44, "bid": 1.32, "ask": 1.48, "volume": 230}, {"strike": 165.0, "lastPrice": 2.19, "bid": 1.96, "ask": 2.27, "volume": 894}, {"strike": 170.0, "lastPrice": 3.08, "bid": 3.0, "ask": 3.2, "volume": 229}, {"strike": 175.0, "lastPrice": 4.55, "bid": 4.4, "ask": 4.65, "volume": 153}, {"strike": 180.0, "lastPrice": 6.42, "bid": 6.35, "ask": 6.65, "volume": 1022}, {"strike": 185.0, "lastPrice": 9.16, "bid": 8.8, "ask": 9.2, "volume": 80}, {"strike": 190.0, "lastPrice": 12.25, "bid": 11.75, "ask": 12.25, "volume": 53}, {"strike": 195.0, "lastPrice": 16.93, "bid": 14.7, "ask": 16.55, "volume": 21}, {"strike": 200.0, "lastPrice": 21.54, "bid": 18.9, "ask": 20.35, "volume": 35}, {"strike": 210.0, "lastPrice": 30.47, "bid": 27.5, "ask": 29.55, "volume": 3}, {"strike": 220.0, "lastPrice": 39.55, "bid": 36.65, "ask": 38.9, "volume": 3}, {"strike": 230.0, "lastPrice": 43.55, "bid": 46.25, "ask": 49.1, "volume": 2}, {"strike": 240.0, "lastPrice": 51.05, "bid": 55.85, "ask": 58.6, "volume": 2}, {"strike": 250.0, "lastPrice": 63.3, "bid": 65.0, "ask": 68.9, "volume": 2}, {"strike": 260.0, "lastPrice": 69.5, "bid": 74.9, "ask": 78.85, "volume": 1}]}, "2026-09-18": {"calls": [{"strike": 80.0, "lastPrice": 103.5, "bid": 0.0, "ask": 0.0, "volume": 4.0}, {"strike": 90.0, "lastPrice": 98.5, "bid": 92.35, "ask": 96.3, "volume": 1.0}, {"strike": 95.0, "lastPrice": 95.0, "bid": 87.4, "ask": 91.3, "volume": 0.0}, {"strike": 100.0, "lastPrice": 67.3, "bid": 88.3, "ask": 91.45, "volume": 1.0}, {"strike": 105.0, "lastPrice": 47.45, "bid": 50.95, "ask": 54.7, "volume": 1.0}, {"strike": 110.0, "lastPrice": 81.41, "bid": 72.5, "ask": 76.4, "volume": 1.0}, {"strike": 115.0, "lastPrice": 67.96, "bid": 0.0, "ask": 0.0, "volume": 1.0}, {"strike": 120.0, "lastPrice": 71.7, "bid": 62.6, "ask": 66.55, "volume": 1.0}, {"strike": 125.0, "lastPrice": 57.25, "bid": 0.0, "ask": 0.0, "volume": 47.0}, {"strike": 130.0, "lastPrice": 60.59, "bid": 0.0, "ask": 0.0, "volume": 1.0}, {"strike": 135.0, "lastPrice": 57.9, "bid": 48.7, "ask": 51.05, "volume": 3.0}, {"strike": 140.0, "lastPrice": 43.71, "bid": 44.05, "ask": 46.75, "volume": 1.0}, {"strike": 145.0, "lastPrice": 48.93, "bid": 39.35, "ask": 42.15, "volume": 1.0}, {"strike": 150.0, "lastPrice": 32.55, "bid": 34.95, "ask": 37.25, "volume": 2.0}, {"strike": 155.0, "lastPrice": 30.13, "bid": 30.65, "ask": 33.15, "volume": 2.0}, {"strike": 160.0, "lastPrice": 23.19, "bid": 26.55, "ask": 29.2, "volume": 3.0}, {"strike": 165.0, "lastPrice": 20.8, "bid": 22.4, "ask": 24.8, "volume": 13.0}, {"strike": 170.0, "lastPrice": 16.89, "bid": 19.25, "ask": 21.2, "volume": 9.0}, {"strike": 175.0, "lastPrice": 17.23, "bid": 16.1, "ask": 18.3, "volume": 165.0}, {"strike": 180.0, "lastPrice": 14.65, "bid": 14.25, "ask": 15.55, "volume": 126.0}, {"strike": 185.0, "lastPrice": 12.15, "bid": 11.6, "ask": 12.55, "volume": 148.0}, {"strike": 190.0, "lastPrice": 10.1, "bid": 9.75, "ask": 10.3, "volume": 282.0}, {"strike": 195.0, "lastPrice": 8.22, "bid": 7.7, "ask": 8.65, "volume": 209.0}, {"strike": 200.0, "lastPrice": 6.7, "bid": 6.6, "ask": 6.85, "volume": 494.0}, {"strike": 210.0, "lastPrice": 4.35, "bid": 4.3, "ask": 4.7, "volume": 324.0}, {"strike": 220.0, "lastPrice": 2.76, "bid": 2.71, "ask": 2.98, "volume": 102.0}, {"strike": 230.0, "lastPrice": 1.53, "bid": 1.32, "ask": 1.97, "volume": 155.0}, {"strike": 240.0, "lastPrice": 1.02, "bid": 0.96, "ask": 1.39, "volume": 51.0}, {"strike": 250.0, "lastPrice": 0.68, "bid": 0.61, "ask": 0.95, "volume": 17.0}, {"strike": 260.0, "lastPrice": 0.39, "bid": 0.3, "ask": 0.73, "volume": 310.0}, {"strike": 270.0, "lastPrice": 0.4, "bid": 0.13, "ask": 0.96, "volume": 305.0}, {"strike": 280.0, "lastPrice": 0.5, "bid": 0.0, "ask": 0.67, "volume": 4.0}, {"strike": 290.0, "lastPrice": 0.2, "bid": 0.15, "ask": 0.6, "volume": 15.0}, {"strike": 300.0, "lastPrice": 0.3, "bid": 0.01, "ask": 0.51, "volume": 164.0}, {"strike": 310.0, "lastPrice": 0.26, "bid": 0.0, "ask": 0.68, "volume": 65.0}], "puts": [{"strike": 70.0, "lastPrice": 0.12, "bid": 0.02, "ask": 0.3, "volume": 3.0}, {"strike": 75.0, "lastPrice": 0.15, "bid": 0.05, "ask": 0.2, "volume": 2.0}, {"strike": 80.0, "lastPrice": 0.2, "bid": 0.0, "ask": 0.17, "volume": 2.0}, {"strike": 85.0, "lastPrice": 0.28, "bid": 0.1, "ask": 0.35, "volume": 2.0}, {"strike": 90.0, "lastPrice": 0.25, "bid": 0.1, "ask": 0.77, "volume": 2.0}, {"strike": 95.0, "lastPrice": 0.25, "bid": 0.0, "ask": 0.61, "volume": 2.0}, {"strike": 100.0, "lastPrice": 0.34, "bid": 0.0, "ask": 0.47, "volume": 1.0}, {"strike": 105.0, "lastPrice": 0.4, "bid": 0.0, "ask": 0.66, "volume": 2.0}, {"strike": 110.0, "lastPrice": 0.5, "bid": 0.2, "ask": 1.0, "volume": 12.0}, {"strike": 115.0, "lastPrice": 0.52, "bid": 0.01, "ask": 1.2, "volume": 3.0}, {"strike": 120.0, "lastPrice": 0.58, "bid": 0.45, "ask": 1.21, "volume": 7.0}, {"strike": 125.0, "lastPrice": 0.63, "bid": 0.39, "ask": 1.05, "volume": 2.0}, {"strike": 130.0, "lastPrice": 0.95, "bid": 0.65, "ask": 1.02, "volume": 1.0}, {"strike": 135.0, "lastPrice": 1.22, "bid": 1.06, "ask": 1.25, "volume": 2.0}, {"strike": 140.0, "lastPrice": 1.58, "bid": 1.37, "ask": 1.72, "volume": 21.0}, {"strike": 145.0, "lastPrice": 2.04, "bid": 1.7, "ask": 2.03, "volume": 9.0}, {"strike": 150.0, "lastPrice": 2.53, "bid": 2.32, "ask": 2.6, "volume": 58.0}, {"strike": 155.0, "lastPrice": 3.25, "bid": 3.05, "ask": 3.3, "volume": 100.0}, {"strike": 160.0, "lastPrice": 4.25, "bid": 3.85, "ask": 4.65, "volume": 220.0}, {"strike": 165.0, "lastPrice": 5.4, "bid": 5.2, "ask": 5.8, "volume": 262.0}, {"strike": 170.0, "lastPrice": 7.1, "bid": 6.6, "ask": 7.5, "volume": 88.0}, {"strike": 175.0, "lastPrice": 8.96, "bid": 8.4, "ask": 9.35, "volume": 63.0}, {"strike": 180.0, "lastPrice": 10.98, "bid": 10.55, "ask": 11.45, "volume": 145.0}, {"strike": 185.0, "lastPrice": 13.69, "bid": 13.05, "ask": 14.05, "volume": 160.0}, {"strike": 190.0, "lastPrice": 16.65, "bid": 15.85, "ask": 16.95, "volume": 35.0}, {"strike": 195.0, "lastPrice": 20.6, "bid": 18.65, "ask": 20.9, "volume": 77.0}, {"strike": 200.0, "lastPrice": 26.65, "bid": 22.25, "ask": 24.4, "volume": 23.0}, {"strike": 210.0, "lastPrice": 33.62, "bid": 29.75, "ask": 32.0, "volume": 3.0}, {"strike": 220.0, "lastPrice": 40.0, "bid": 38.35, "ask": 40.45, "volume": 4.0}, {"strike": 230.0, "lastPrice": 36.55, "bid": 47.1, "ask": 49.5, "volume": 2.0}, {"strike": 240.0, "lastPrice": 38.8, "bid": 56.45, "ask": 59.0, "volume": 10.0}, {"strike": 250.0, "lastPrice": 53.7, "bid": 66.25, "ask": 68.75, "volume": 2.0}, {"strike": 260.0, "lastPrice": 58.3, "bid": 75.8, "ask": 78.6, "volume": 0.0}, {"strike": 270.0, "lastPrice": 69.13, "bid": 84.9, "ask": 88.8, "volume": 2.0}, {"strike": 280.0, "lastPrice": 82.76, "bid": 94.75, "ask": 98.8, "volume": 0.0}, {"strike": 300.0, "lastPrice": 94.25, "bid": 114.7, "ask": 118.7, "volume": 0.0}, {"strike": 310.0, "lastPrice": 98.79, "bid": 124.65, "ask": 128.6, "volume": 0.0}]}}