{"2026-02-20": {"calls": [{"strike": 60.0, "lastPrice": 55.27, "bid": 0.0, "ask": 0.0, "volume": 1.0}, {"strike": 65.0, "lastPrice": 55.34, "bid": 0.0, "ask": 0.0, "volume": 8.0}, {"strike": 70.0, "lastPrice": 52.77, "bid": 0.0, "ask": 0.0, "volume": 1.0}, {"strike": 75.0, "lastPrice": 29.93, "bid": 38.0, "ask": 40.0, "volume": 0.0}, {"strike": 80.0, "lastPrice": 36.95, "bid": 0.0, "ask": 0.0, "volume": 1.0}, {"strike": 85.0, "lastPrice": 35.5, "bid": 0.0, "ask": 0.0, "volume": 15.0}, {"strike": 90.0, "lastPrice": 26.85, "bid": 0.0, "ask": 0.0, "volume": 1.0}, {"strike": 95.0, "lastPrice": 23.32, "bid": 0.0, "ask": 0.0, "volume": 1.0}, {"strike": 97.5, "lastPrice": 30.63, "bid": 0.0, "ask": 0.0, "volume": 1.0}, {"strike": 100.0, "lastPrice": 27.49, "bid": 0.0, "ask": 0.0, "volume": 1.0}, {"strike": 105.0, "lastPrice": 24.22, "bid": 0.0, "ask": 0.0, "volume": 4.0}, {"strike": 106.0, "lastPrice": 22.64, "bid": 0.0, "ask": 0.0, "volume": 78.0}, {"strike": 107.0, "lastPrice": 21.39, "bid": 0.0, "ask": 0.0, "volume": 14.0}, {"strike": 108.0, "lastPrice": 20.82, "bid": 0.0, "ask": 0.0, "volume": 88.0}, {"strike": 109.0, "lastPrice": 19.74, "bid": 0.0, "ask": 0.0, "volume": 82.0}, {"strike": 110.0, "lastPrice": 17.41, "bid": 0.0, "ask": 0.0, "volume": 3.0}, {"strike": 111.0, "lastPrice": 18.09, "bid": 0.0, "ask": 0.0, "volume": 185.0}, {"strike": 112.0, "lastPrice": 17.57, "bid": 0.0, "ask": 0.0, "volume": 10.0}, {"strike": 113.0, "lastPrice": 15.72, "bid": 0.0, "ask": 0.0, "volume": 4.0}, {"strike": 114.0, "lastPrice": 13.93, "bid": 0.0, "ask": 0.0, "volume": 5.0}, {"strike": 115.0, "lastPrice": 13.0, "bid": 0.0, "ask": 0.0, "volume": 52.0}, {"strike": 116.0, "lastPrice": 12.94, "bid": 0.0, "ask": 0.0, "volume": 4.0}, {"strike": 117.0, "lastPrice": 11.26, "bid": 0.0, "ask": 0.0, "volume": 10.0}, {"strike": 118.0, "lastPrice": 10.3, "bid": 0.0, "ask": 0.0, "volume": 5.0}, {"strike": 119.0, "lastPrice": 9.8, "bid": 0.0, "ask": 0.0, "volume": 7.0}, {"strike": 120.0, "lastPrice": 8.49, "bid": 0.0, "ask": 0.0, "volume": 219.0}, {"strike": 121.0, "lastPrice": 7.85, "bid": 0.0, "ask": 0.0, "volume": 56.0}, {"strike": 122.0, "lastPrice": 7.21, "bid": 0.0, "ask": 0.0, "volume": 87.0}, {"strike": 123.0, "lastPrice": 6.17, "bid": 0.0, "ask": 0.0, "volume": 278.0}, {"strike": 124.0, "lastPrice": 7.5, "bid": 0.0, "ask": 0.0, "volume": 3.0}, {"strike": 125.0, "lastPrice": 5.07, "bid": 0.0, "ask": 0.0, "volume": 423.0}, {"strike": 126.0, "lastPrice": 4.8, "bid": 0.0, "ask": 0.0, "volume": 247.0}, {"strike": 127.0, "lastPrice": 4.08, "bid": 0.0, "ask": 0.0, "volume": 154.0}, {"strike": 128.0, "lastPrice": 3.57, "bid": 0.0, "ask": 0.0, "volume": 394.0}, {"strike": 129.0, "lastPrice": 3.18, "bid": 0.0, "ask": 0.0, "volume": 207.0}, {"strike": 130.0, "lastPrice": 2.75, "bid": 0.0, "ask": 0.0, "volume": 667.0}, {"strike": 135.0, "lastPrice": 1.21, "bid": 0.0, "ask": 0.0, "volume": 695.0}, {"strike": 140.0, "lastPrice": 0.51, "bid": 0.0, "ask": 0.0, "volume": 543.0}, {"strike": 145.0, "lastPrice": 0.19, "bid": 0.0, "ask": 0.0, "volume": 186.0}, {"strike": 150.0, "lastPrice": 0.1, "bid": 0.0, "ask": 0.0, "volume": 61.0}, {"strike": 155.0, "lastPrice": 0.06, "bid": 0.0, "ask": 0.0, "volume": 8.0}, {"strike": 160.0, "lastPrice": 0.03, "bid": 0.0, "ask": 0.0, "volume": 5.0}, {"strike": 170.0, "lastPrice": 0.04, "bid": 0.0, "ask": 0.0, "volume": 14.0}], "puts": [{"strike": 60.0, "lastPrice": 0.01, "bid": 0.0, "ask": 0.0, "volume": 0.0}, {"strike": 65.0, "lastPrice": 0.01, "bid": 0.0, "ask": 0.0, "volume": 1.0}, {"strike": 70.0, "lastPrice": 0.04, "bid": 0.0, "ask": 0.0, "volume": 37.0}, {"strike": 75.0, "lastPrice": 0.04, "bid": 0.0, "ask": 0.0, "volume": 4.0}, {"strike": 80.0, "lastPrice": 0.02, "bid": 0.0, "ask": 0.0, "volume": 11.0}, {"strike": 85.0, "lastPrice": 0.01, "bid": 0.0, "ask": 0.0, "volume": 6.0}, {"strike": 90.0, "lastPrice": 0.05, "bid": 0.0, "ask": 0.0, "volume": 3.0}, {"strike": 95.0, "lastPrice": 0.15, "bid": 0.0, "ask": 0.0, "volume": 3.0}, {"strike": 97.5, "lastPrice": 0.11, "bid": 0.0, "ask": 0.0, "volume": 9.0}, {"strike": 100.0, "lastPrice": 0.13, "bid": 0.0, "ask": 0.0, "volume": 35.0}, {"strike": 105.0, "lastPrice": 0.16, "bid": 0.0, "ask": 0.0, "volume": 163.0}, {"strike": 106.0, "lastPrice": 0.16, "bid": 0.0, "ask": 0.0, "volume": 1.0}, {"strike": 107.0, "lastPrice": 0.2, "bid": 0.0, "ask": 0.0, "volume": 11.0}, {"strike": 108.0, "lastPrice": 0.12, "bid": 0.0, "ask": 0.0, "volume": 15.0}, {"strike": 109.0, "lastPrice": 0.29, "bid": 0.0, "ask": 0.0, "volume": 1.0}, {"strike": 110.0, "lastPrice": 0.27, "bid": 0.0, "ask": 0.0, "volume": 270.0}, {"strike": 111.0, "lastPrice": 0.33, "bid": 0.0, "ask": 0.0, "volume": 8.0}, {"strike": 112.0, "lastPrice": 0.38, "bid": 0.0, "ask": 0.0, "volume": 3792.0}, {"strike": 113.0, "lastPrice": 0.41, "bid": 0.0, "ask": 0.0, "volume": 43.0}, {"strike": 114.0, "lastPrice": 0.55, "bid": 0.0, "ask": 0.0, "volume": 9.0}, {"strike": 115.0, "lastPrice": 0.62, "bid": 0.0, "ask": 0.0, "volume": 985.0}, {"strike": 116.0, "lastPrice": 0.67, "bid": 0.0, "ask": 0.0, "volume": 27.0}, {"strike": 117.0, "lastPrice": 0.82, "bid": 0.0, "ask": 0.0, "volume": 25.0}, {"strike": 118.0, "lastPrice": 0.97, "bid": 0.0, "ask": 0.0, "volume": 33.0}, {"strike": 119.0, "lastPrice": 1.18, "bid": 0.0, "ask": 0.0, "volume": 126.0}, {"strike": 120.0, "lastPrice": 1.37, "bid": 0.0, "ask": 0.0, "volume": 3636.0}, {"strike": 121.0, "lastPrice": 1.57, "bid": 0.0, "ask": 0.0, "volume": 116.0}, {"strike": 122.0, "lastPrice": 1.79, "bid": 0.0, "ask": 0.0, "volume": 108.0}, {"strike": 123.0, "lastPrice": 2.03, "bid": 0.0, "ask": 0.0, "volume": 64.0}, {"strike": 124.0, "lastPrice": 2.55, "bid": 0.0, "ask": 0.0, "volume": 7311.0}, {"strike": 125.0, "lastPrice": 3.01, "bid": 0.0, "ask": 0.0, "volume": 850.0}, {"strike": 126.0, "lastPrice": 3.37, "bid": 0.0, "ask": 0.0, "volume": 215.0}, {"strike": 127.0, "lastPrice": 4.0, "bid": 0.0, "ask": 0.0, "volume": 124.0}, {"strike": 128.0, "lastPrice": 4.36, "bid": 0.0, "ask": 0.0, "volume": 320.0}, {"strike": 129.0, "lastPrice": 4.96, "bid": 0.0, "ask": 0.0, "volume": 138.0}, {"strike": 130.0, "lastPrice": 5.45, "bid": 0.0, "ask": 0.0, "volume": 351.0}, {"strike": 140.0, "lastPrice": 11.45, "bid": 0.0, "ask": 0.0, "volume": 4.0}, {"strike": 155.0, "lastPrice": 36.18, "bid": 0.0, "ask": 0.0, "volume": 1.0}, {"strike": 160.0, "lastPrice": 41.2, "bid": 0.0, "ask": 0.0, "volume": 1.0}]}, "2026-02-27": {"calls": [{"strike": 60.0, "lastPrice": 57.25, "bid": 0.0, "ask": 0.0, "volume": 0.0}, {"strike": 70.0, "lastPrice": 57.31, "bid": 0.0, "ask": 0.0, "volume": 4.0}, {"strike": 90.0, "lastPrice": 38.93, "bid": 0.0, "ask": 0.0, "volume": 6.0}, {"strike": 95.0, "lastPrice": 24.55, "bid": 0.0, "ask": 0.0, "volume": 0.0}, {"strike": 98.0, "lastPrice": 21.18, "bid": 0.0, "ask": 0.0, "volume": 0.0}, {"strike": 100.0, "lastPrice": 28.32, "bid": 0.0, "ask": 0.0, "volume": 1.0}, {"strike": 101.0, "lastPrice": 27.93, "bid": 0.0, "ask": 0.0, "volume": 200.0}, {"strike": 103.0, "lastPrice": 17.8, "bid": 0.0, "ask": 0.0, "volume": 0.0}, {"strike": 104.0, "lastPrice": 25.1, "bid": 0.0, "ask": 0.0, "volume": 2.0}, {"strike": 105.0, "lastPrice": 13.2, "bid": 0.0, "ask": 0.0, "volume": 3.0}, {"strike": 106.0, "lastPrice": 23.05, "bid": 0.0, "ask": 0.0, "volume": 200.0}, {"strike": 107.0, "lastPrice": 21.72, "bid": 0.0, "ask": 0.0, "volume": 339.0}, {"strike": 108.0, "lastPrice": 13.6, "bid": 0.0, "ask": 0.0, "volume": 1.0}, {"strike": 109.0, "lastPrice": 16.75, "bid": 0.0, "ask": 0.0, "volume": 1.0}, {"strike": 110.0, "lastPrice": 18.93, "bid": 0.0, "ask": 0.0, "volume": 7.0}, {"strike": 111.0, "lastPrice": 16.95, "bid": 0.0, "ask": 0.0, "volume": 4.0}, {"strike": 112.0, "lastPrice": 17.36, "bid": 0.0, "ask": 0.0, "volume": 4.0}, {"strike": 113.0, "lastPrice": 14.92, "bid": 0.0, "ask": 0.0, "volume": 10.0}, {"strike": 114.0, "lastPrice": 14.4, "bid": 0.0, "ask": 0.0, "volume": 1.0}, {"strike": 115.0, "lastPrice": 13.27, "bid": 0.0, "ask": 0.0, "volume": 3.0}, {"strike": 116.0, "lastPrice": 13.42, "bid": 0.0, "ask": 0.0, "volume": 1.0}, {"strike": 117.0, "lastPrice": 11.2, "bid": 0.0, "ask": 0.0, "volume": 2.0}, {"strike": 118.0, "lastPrice": 10.9, "bid": 0.0, "ask": 0.0, "volume": 2.0}, {"strike": 119.0, "lastPrice": 9.95, "bid": 0.0, "ask": 0.0, "volume": 6.0}, {"strike": 120.0, "lastPrice": 8.86, "bid": 0.0, "ask": 0.0, "volume": 28.0}, {"strike": 121.0, "lastPrice": 9.0, "bid": 0.0, "ask": 0.0, "volume": 1.0}, {"strike": 122.0, "lastPrice": 7.9, "bid": 0.0, "ask": 0.0, "volume": 4.0}, {"strike": 123.0, "lastPrice": 7.1, "bid": 0.0, "ask": 0.0, "volume": 164.0}, {"strike": 124.0, "lastPrice": 6.49, "bid": 0.0, "ask": 0.0, "volume": 11.0}, {"strike": 125.0, "lastPrice": 5.8, "bid": 0.0, "ask": 0.0, "volume": 25.0}, {"strike": 126.0, "lastPrice": 6.33, "bid": 0.0, "ask": 0.0, "volume": 6.0}, {"strike": 127.0, "lastPrice": 4.63, "bid": 0.0, "ask": 0.0, "volume": 155.0}, {"strike": 128.0, "lastPrice": 4.15, "bid": 0.0, "ask": 0.0, "volume": 28.0}, {"strike": 129.0, "lastPrice": 3.5, "bid": 0.0, "ask": 0.0, "volume": 24.0}, {"strike": 130.0, "lastPrice": 2.98, "bid": 0.0, "ask": 0.0, "volume": 90.0}, {"strike": 131.0, "lastPrice": 2.91, "bid": 0.0, "ask": 0.0, "volume": 28.0}, {"strike": 132.0, "lastPrice": 2.52, "bid": 0.0, "ask": 0.0, "volume": 6.0}, {"strike": 133.0, "lastPrice": 2.45, "bid": 0.0, "ask": 0.0, "volume": 10.0}, {"strike": 134.0, "lastPrice": 1.85, "bid": 0.0, "ask": 0.0, "volume": 36.0}, {"strike": 135.0, "lastPrice": 1.46, "bid": 0.0, "ask": 0.0, "volume": 57.0}], "puts": [{"strike": 95.0, "lastPrice": 0.3, "bid": 0.0, "ask": 0.0, "volume": 0.0}, {"strike": 98.0, "lastPrice": 0.35, "bid": 0.0, "ask": 0.0, "volume": 12.0}, {"strike": 99.0, "lastPrice": 0.14, "bid": 0.05, "ask": 0.0, "volume": 10.0}, {"strike": 100.0, "lastPrice": 0.12, "bid": 0.0, "ask": 0.0, "volume": 33.0}, {"strike": 101.0, "lastPrice": 0.46, "bid": 0.05, "ask": 0.0, "volume": 1.0}, {"strike": 103.0, "lastPrice": 0.23, "bid": 0.0, "ask": 0.0, "volume": 9.0}, {"strike": 104.0, "lastPrice": 0.19, "bid": 0.0, "ask": 0.0, "volume": 12.0}, {"strike": 105.0, "lastPrice": 0.19, "bid": 0.0, "ask": 0.0, "volume": 1.0}, {"strike": 106.0, "lastPrice": 0.26, "bid": 0.0, "ask": 0.0, "volume": 2.0}, {"strike": 107.0, "lastPrice": 0.26, "bid": 0.0, "ask": 0.0, "volume": 4.0}, {"strike": 108.0, "lastPrice": 0.31, "bid": 0.0, "ask": 0.0, "volume": 6.0}, {"strike": 109.0, "lastPrice": 0.3, "bid": 0.0, "ask": 0.0, "volume": 11.0}, {"strike": 110.0, "lastPrice": 0.41, "bid": 0.0, "ask": 0.0, "volume": 22.0}, {"strike": 111.0, "lastPrice": 0.46, "bid": 0.0, "ask": 0.0, "volume": 1.0}, {"strike": 112.0, "lastPrice": 0.54, "bid": 0.0, "ask": 0.0, "volume": 3.0}, {"strike": 113.0, "lastPrice": 0.56, "bid": 0.0, "ask": 0.0, "volume": 2.0}, {"strike": 114.0, "lastPrice": 0.68, "bid": 0.0, "ask": 0.0, "volume": 11.0}, {"strike": 115.0, "lastPrice": 0.81, "bid": 0.0, "ask": 0.0, "volume": 27.0}, {"strike": 116.0, "lastPrice": 0.93, "bid": 0.0, "ask": 0.0, "volume": 27.0}, {"strike": 117.0, "lastPrice": 1.02, "bid": 0.0, "ask": 0.0, "volume": 13.0}, {"strike": 118.0, "lastPrice": 1.23, "bid": 0.0, "ask": 0.0, "volume": 22.0}, {"strike": 119.0, "lastPrice": 1.09, "bid": 0.0, "ask": 0.0, "volume": 4.0}, {"strike": 120.0, "lastPrice": 1.67, "bid": 0.0, "ask": 0.0, "volume": 172.0}, {"strike": 121.0, "lastPrice": 1.82, "bid": 0.0, "ask": 0.0, "volume": 3.0}, {"strike": 122.0, "lastPrice": 2.38, "bid": 0.0, "ask": 0.0, "volume": 15.0}, {"strike": 123.0, "lastPrice": 2.71, "bid": 0.0, "ask": 0.0, "volume": 11.0}, {"strike": 124.0, "lastPrice": 2.77, "bid": 0.0, "ask": 0.0, "volume": 5.0}, {"strike": 125.0, "lastPrice": 3.5, "bid": 0.0, "ask": 0.0, "volume": 44.0}, {"strike": 127.0, "lastPrice": 4.47, "bid": 0.0, "ask": 0.0, "volume": 21.0}, {"strike": 131.0, "lastPrice": 6.65, "bid": 0.0, "ask": 0.0, "volume": 3.0}, {"strike": 135.0, "lastPrice": 17.06, "bid": 0.0, "ask": 0.0, "volume": 1.0}]}, "2026-03-06": {"calls": [{"strike": 70.0, "lastPrice": 57.37, "bid": 0.0, "ask": 0.0, "volume": 2.0}, {"strike": 100.0, "lastPrice": 23.4, "bid": 0.0, "ask": 0.0, "volume": 0.0}, {"strike": 105.0, "lastPrice": 13.77, "bid": 0.0, "ask": 0.0, "volume": 0.0}, {"strike": 106.0, "lastPrice": 11.9, "bid": 0.0, "ask": 0.0, "volume": 1.0}, {"strike": 109.0, "lastPrice": 18.71, "bid": 0.0, "ask": 0.0, "volume": 1.0}, {"strike": 110.0, "lastPrice": 18.05, "bid": 0.0, "ask": 0.0, "volume": 2.0}, {"strike": 112.0, "lastPrice": 16.34, "bid": 0.0, "ask": 0.0, "volume": 2.0}, {"strike": 113.0, "lastPrice": 15.35, "bid": 0.0, "ask": 0.0, "volume": 1.0}, {"strike": 114.0, "lastPrice": 15.35, "bid": 0.0, "ask": 0.0, "volume": 2.0}, {"strike": 115.0, "lastPrice": 14.5, "bid": 0.0, "ask": 0.0, "volume": 1.0}, {"strike": 116.0, "lastPrice": 9.55, "bid": 0.0, "ask": 0.0, "volume": 5.0}, {"strike": 117.0, "lastPrice": 11.62, "bid": 0.0, "ask": 0.0, "volume": 2.0}, {"strike": 118.0, "lastPrice": 10.91, "bid": 0.0, "ask": 0.0, "volume": 2.0}, {"strike": 119.0, "lastPrice": 10.59, "bid": 0.0, "ask": 0.0, "volume": 1.0}, {"strike": 120.0, "lastPrice": 9.7, "bid": 0.0, "ask": 0.0, "volume": 6.0}, {"strike": 121.0, "lastPrice": 8.78, "bid": 0.0, "ask": 0.0, "volume": 7.0}, {"strike": 122.0, "lastPrice": 7.98, "bid": 0.0, "ask": 0.0, "volume": 4.0}, {"strike": 123.0, "lastPrice": 7.4, "bid": 0.0, "ask": 0.0, "volume": 2.0}, {"strike": 124.0, "lastPrice": 8.0, "bid": 0.0, "ask": 0.0, "volume": 1.0}, {"strike": 125.0, "lastPrice": 6.02, "bid": 0.0, "ask": 0.0, "volume": 107.0}, {"strike": 126.0, "lastPrice": 5.56, "bid": 0.0, "ask": 0.0, "volume": 1.0}, {"strike": 127.0, "lastPrice": 4.75, "bid": 0.0, "ask": 0.0, "volume": 2.0}, {"strike": 128.0, "lastPrice": 4.6, "bid": 0.0, "ask": 0.0, "volume": 31.0}, {"strike": 129.0, "lastPrice": 3.5, "bid": 0.0, "ask": 0.0, "volume": 115.0}, {"strike": 130.0, "lastPrice": 3.57, "bid": 0.0, "ask": 0.0, "volume": 21.0}, {"strike": 131.0, "lastPrice": 3.55, "bid": 0.0, "ask": 0.0, "volume": 4.0}, {"strike": 132.0, "lastPrice": 2.78, "bid": 0.0, "ask": 0.0, "volume": 15.0}, {"strike": 135.0, "lastPrice": 2.0, "bid": 0.0, "ask": 0.0, "volume": 9.0}], "puts": [{"strike": 85.0, "lastPrice": 0.39, "bid": 0.0, "ask": 0.0, "volume": 0.0}, {"strike": 95.0, "lastPrice": 0.29, "bid": 0.0, "ask": 0.0, "volume": 0.0}, {"strike": 100.0, "lastPrice": 0.17, "bid": 0.0, "ask": 0.0, "volume": 10.0}, {"strike": 104.0, "lastPrice": 0.73, "bid": 0.0, "ask": 0.0, "volume": 0.0}, {"strike": 105.0, "lastPrice": 0.33, "bid": 0.0, "ask": 0.0, "volume": 2.0}, {"strike": 106.0, "lastPrice": 0.24, "bid": 0.0, "ask": 0.0, "volume": 5.0}, {"strike": 107.0, "lastPrice": 0.43, "bid": 0.0, "ask": 0.0, "volume": 10.0}, {"strike": 108.0, "lastPrice": 0.4, "bid": 0.0, "ask": 0.0, "volume": 4.0}, {"strike": 109.0, "lastPrice": 0.47, "bid": 0.0, "ask": 0.0, "volume": 16.0}, {"strike": 110.0, "lastPrice": 0.49, "bid": 0.0, "ask": 0.0, "volume": 33.0}, {"strike": 111.0, "lastPrice": 0.63, "bid": 0.0, "ask": 0.0, "volume": 31.0}, {"strike": 112.0, "lastPrice": 0.6, "bid": 0.0, "ask": 0.0, "volume": 2.0}, {"strike": 113.0, "lastPrice": 1.02, "bid": 0.0, "ask": 0.0, "volume": 1.0}, {"strike": 114.0, "lastPrice": 0.74, "bid": 0.0, "ask": 0.0, "volume": 2.0}, {"strike": 115.0, "lastPrice": 1.1, "bid": 0.0, "ask": 0.0, "volume": 32.0}, {"strike": 116.0, "lastPrice": 1.0, "bid": 0.0, "ask": 0.0, "volume": 1.0}, {"strike": 117.0, "lastPrice": 1.3, "bid": 0.0, "ask": 0.0, "volume": 102.0}, {"strike": 118.0, "lastPrice": 1.32, "bid": 0.0, "ask": 0.0, "volume": 3.0}, {"strike": 119.0, "lastPrice": 1.63, "bid": 0.0, "ask": 0.0, "volume": 22.0}, {"strike": 120.0, "lastPrice": 2.0, "bid": 0.0, "ask": 0.0, "volume": 173.0}, {"strike": 121.0, "lastPrice": 2.32, "bid": 0.0, "ask": 0.0, "volume": 2.0}, {"strike": 122.0, "lastPrice": 2.53, "bid": 0.0, "ask": 0.0, "volume": 2.0}, {"strike": 127.0, "lastPrice": 4.47, "bid": 0.0, "ask": 0.0, "volume": 3.0}]}, "2026-03-13": {"calls": [{"strike": 100.0, "lastPrice": 18.73, "bid": 0.0, "ask": 0.0, "volume": 0.0}, {"strike": 109.0, "lastPrice": 19.62, "bid": 0.0, "ask": 0.0, "volume": 1.0}, {"strike": 111.0, "lastPrice": 9.41, "bid": 0.0, "ask": 0.0, "volume": 0.0}, {"strike": 117.0, "lastPrice": 11.95, "bid": 0.0, "ask": 0.0, "volume": 13.0}, {"strike": 118.0, "lastPrice": 11.25, "bid": 0.0, "ask": 0.0, "volume": 5.0}, {"strike": 119.0, "lastPrice": 10.59, "bid": 0.0, "ask": 0.0, "volume": 2.0}, {"strike": 120.0, "lastPrice": 9.72, "bid": 0.0, "ask": 0.0, "volume": 6.0}, {"strike": 122.0, "lastPrice": 8.37, "bid": 0.0, "ask": 0.0, "volume": 3.0}, {"strike": 124.0, "lastPrice": 7.28, "bid": 0.0, "ask": 0.0, "volume": 1.0}, {"strike": 125.0, "lastPrice": 6.5, "bid": 0.0, "ask": 0.0, "volume": 10.0}, {"strike": 126.0, "lastPrice": 5.83, "bid": 0.0, "ask": 0.0, "volume": 4.0}, {"strike": 127.0, "lastPrice": 5.31, "bid": 0.0, "ask": 0.0, "volume": 4.0}], "puts": [{"strike": 100.0, "lastPrice": 0.37, "bid": 0.0, "ask": 0.0, "volume": 0.0}, {"strike": 103.0, "lastPrice": 0.4, "bid": 0.0, "ask": 0.0, "volume": 5.0}, {"strike": 105.0, "lastPrice": 0.6, "bid": 0.0, "ask": 0.0, "volume": 7.0}, {"strike": 107.0, "lastPrice": 0.77, "bid": 0.0, "ask": 0.0, "volume": 3.0}, {"strike": 108.0, "lastPrice": 1.43, "bid": 0.0, "ask": 0.0, "volume": 0.0}, {"strike": 109.0, "lastPrice": 0.83, "bid": 0.0, "ask": 0.0, "volume": 0.0}, {"strike": 110.0, "lastPrice": 0.75, "bid": 0.0, "ask": 0.0, "volume": 207.0}, {"strike": 113.0, "lastPrice": 1.07, "bid": 0.0, "ask": 0.0, "volume": 4.0}, {"strike": 115.0, "lastPrice": 0.95, "bid": 0.0, "ask": 0.0, "volume": 3.0}, {"strike": 117.0, "lastPrice": 1.66, "bid": 0.0, "ask": 0.0, "volume": 1.0}, {"strike": 118.0, "lastPrice": 1.87, "bid": 0.0, "ask": 0.0, "volume": 1.0}, {"strike": 119.0, "lastPrice": 2.17, "bid": 0.0, "ask": 0.0, "volume": 1.0}]}, "2026-03-20": {"calls": [{"strike": 45.0, "lastPrice": 52.13, "bid": 58.85, "ask": 59.15, "volume": 2}, {"strike": 47.5, "lastPrice": 68.35, "bid": 69.05, "ask": 72.35, "volume": 50}, {"strike": 50.0, "lastPrice": 65.05, "bid": 66.5, "ask": 69.3, "volume": 21}, {"strike": 55.0, "lastPrice": 63.97, "bid": 0.0, "ask": 0.0, "volume": 18}, {"strike": 60.0, "lastPrice": 62.43, "bid": 0.0, "ask": 0.0, "volume": 2}, {"strike": 65.0, "lastPrice": 64.26, "bid": 0.0, "ask": 0.0, "volume": 3}, {"strike": 70.0, "lastPrice": 58.36, "bid": 0.0, "ask": 0.0, "volume": 4}, {"strike": 75.0, "lastPrice": 52.5, "bid": 0.0, "ask": 0.0, "volume": 3}, {"strike": 77.5, "lastPrice": 39.5, "bid": 40.85, "ask": 42.85, "volume": 4}, {"strike": 80.0, "lastPrice": 40.66, "bid": 0.0, "ask": 0.0, "volume": 2}, {"strike": 82.5, "lastPrice": 36.7, "bid": 0.0, "ask": 0.0, "volume": 1}, {"strike": 85.0, "lastPrice": 45.0, "bid": 0.0, "ask": 0.0, "volume": 1}, {"strike": 87.5, "lastPrice": 40.35, "bid": 0.0, "ask": 0.0, "volume": 1}, {"strike": 90.0, "lastPrice": 37.98, "bid": 0.0, "ask": 0.0, "volume": 1}, {"strike": 92.5, "lastPrice": 30.75, "bid": 0.0, "ask": 0.0, "volume": 2}, {"strike": 95.0, "lastPrice": 33.2, "bid": 0.0, "ask": 0.0, "volume": 7}, {"strike": 97.5, "lastPrice": 31.0, "bid": 0.0, "ask": 0.0, "volume": 1}, {"strike": 100.0, "lastPrice": 28.6, "bid": 0.0, "ask": 0.0, "volume": 3}, {"strike": 105.0, "lastPrice": 23.35, "bid": 0.0, "ask": 0.0, "volume": 6}, {"strike": 110.0, "lastPrice": 18.57, "bid": 0.0, "ask": 0.0, "volume": 415}, {"strike": 115.0, "lastPrice": 13.75, "bid": 0.0, "ask": 0.0, "volume": 647}, {"strike": 120.0, "lastPrice": 9.97, "bid": 0.0, "ask": 0.0, "volume": 193}, {"strike": 125.0, "lastPrice": 6.73, "bid": 0.0, "ask": 0.0, "volume": 580}, {"strike": 130.0, "lastPrice": 4.3, "bid": 0.0, "ask": 0.0, "volume": 582}, {"strike": 135.0, "lastPrice": 2.54, "bid": 0.0, "ask": 0.0, "volume": 347}, {"strike": 140.0, "lastPrice": 1.24, "bid": 0.0, "ask": 0.0, "volume": 2230}, {"strike": 145.0, "lastPrice": 0.66, "bid": 0.0, "ask": 0.0, "volume": 600}, {"strike": 150.0, "lastPrice": 0.36, "bid": 0.0, "ask": 0.0, "volume": 204}, {"strike": 155.0, "lastPrice": 0.21, "bid": 0.0, "ask": 0.0, "volume": 9}, {"strike": 160.0, "lastPrice": 0.1, "bid": 0.0, "ask": 0.0, "volume": 70}], "puts": [{"strike": 45.0, "lastPrice": 0.05, "bid": 0.0, "ask": 0.51, "volume": 21.0}, {"strike": 47.5, "lastPrice": 0.05, "bid": 0.0, "ask": 0.58, "volume": 3.0}, {"strike": 50.0, "lastPrice": 0.11, "bid": 0.0, "ask": 0.29, "volume": 2.0}, {"strike": 55.0, "lastPrice": 0.01, "bid": 0.0, "ask": 0.0, "volume": 6.0}, {"strike": 60.0, "lastPrice": 0.02, "bid": 0.0, "ask": 0.0, "volume": 5.0}, {"strike": 65.0, "lastPrice": 0.04, "bid": 0.0, "ask": 0.0, "volume": 1.0}, {"strike": 70.0, "lastPrice": 0.12, "bid": 0.0, "ask": 0.0, "volume": 1.0}, {"strike": 75.0, "lastPrice": 0.28, "bid": 0.0, "ask": 0.0, "volume": 1.0}, {"strike": 77.5, "lastPrice": 0.09, "bid": 0.0, "ask": 0.0, "volume": 1.0}, {"strike": 80.0, "lastPrice": 0.08, "bid": 0.0, "ask": 0.0, "volume": 11.0}, {"strike": 82.5, "lastPrice": 0.09, "bid": 0.0, "ask": 0.0, "volume": 1.0}, {"strike": 85.0, "lastPrice": 0.11, "bid": 0.0, "ask": 0.0, "volume": 7.0}, {"strike": 87.5, "lastPrice": 0.14, "bid": 0.0, "ask": 0.0, "volume": 3502.0}, {"strike": 90.0, "lastPrice": 0.18, "bid": 0.0, "ask": 0.0, "volume": 24.0}, {"strike": 92.5, "lastPrice": 0.2, "bid": 0.0, "ask": 0.0, "volume": 2.0}, {"strike": 95.0, "lastPrice": 0.24, "bid": 0.0, "ask": 0.0, "volume": 24.0}, {"strike": 97.5, "lastPrice": 0.27, "bid": 0.0, "ask": 0.0, "volume": 14.0}, {"strike": 100.0, "lastPrice": 0.37, "bid": 0.0, "ask": 0.0, "volume": 213.0}, {"strike": 105.0, "lastPrice": 0.53, "bid": 0.0, "ask": 0.0, "volume": 100.0}, {"strike": 110.0, "lastPrice": 0.88, "bid": 0.0, "ask": 0.0, "volume": 350.0}, {"strike": 115.0, "lastPrice": 1.63, "bid": 0.0, "ask": 0.0, "volume": 292.0}, {"strike": 120.0, "lastPrice": 2.64, "bid": 0.0, "ask": 0.0, "volume": 2606.0}, {"strike": 125.0, "lastPrice": 4.5, "bid": 0.0, "ask": 0.0, "volume": 1486.0}, {"strike": 130.0, "lastPrice": 6.95, "bid": 0.0, "ask": 0.0, "volume": 380.0}, {"strike": 135.0, "lastPrice": 9.95, "bid": 0.0, "ask": 0.0, "volume": 25.0}, {"strike": 140.0, "lastPrice": 13.25, "bid": 0.0, "ask": 0.0, "volume": 7.0}, {"strike": 150.0, "lastPrice": 22.1, "bid": 0.0, "ask": 0.0, "volume": 1.0}, {"strike": 155.0, "lastPrice": 36.5, "bid": 0.0, "ask": 0.0, "volume": 0.0}]}, "2026-06-18": {"calls": [{"strike": 45.0, "lastPrice": 78.45, "bid": 0.0, "ask": 0.0, "volume": 1}, {"strike": 47.5, "lastPrice": 65.4, "bid": 0.0, "ask": 0.0, "volume": 49}, {"strike": 50.0, "lastPrice": 69.5, "bid": 0.0, "ask": 0.0, "volume": 15}, {"strike": 55.0, "lastPrice": 72.95, "bid": 0.0, "ask": 0.0, "volume": 150}, {"strike": 60.0, "lastPrice": 67.85, "bid": 0.0, "ask": 0.0, "volume": 287}, {"strike": 65.0, "lastPrice": 52.35, "bid": 0.0, "ask": 0.0, "volume": 31}, {"strike": 70.0, "lastPrice": 57.62, "bid": 0.0, "ask": 0.0, "volume": 27}, {"strike": 75.0, "lastPrice": 53.0, "bid": 0.0, "ask": 0.0, "volume": 30}, {"strike": 77.5, "lastPrice": 52.28, "bid": 0.0, "ask": 0.0, "volume": 3}, {"strike": 80.0, "lastPrice": 45.0, "bid": 0.0, "ask": 0.0, "volume": 5}, {"strike": 82.5, "lastPrice": 36.05, "bid": 0.0, "ask": 0.0, "volume": 1}, {"strike": 85.0, "lastPrice": 35.0, "bid": 0.0, "ask": 0.0, "volume": 2}, {"strike": 87.5, "lastPrice": 42.0, "bid": 0.0, "ask": 0.0, "volume": 1}, {"strike": 90.0, "lastPrice": 38.98, "bid": 0.0, "ask": 0.0, "volume": 5}, {"strike": 92.5, "lastPrice": 27.14, "bid": 0.0, "ask": 0.0, "volume": 2}, {"strike": 95.0, "lastPrice": 34.34, "bid": 0.0, "ask": 0.0, "volume": 31}, {"strike": 97.5, "lastPrice": 31.8, "bid": 0.0, "ask": 0.0, "volume": 2}, {"strike": 100.0, "lastPrice": 29.75, "bid": 0.0, "ask": 0.0, "volume": 62}, {"strike": 105.0, "lastPrice": 26.35, "bid": 0.0, "ask": 0.0, "volume": 75}, {"strike": 110.0, "lastPrice": 21.18, "bid": 0.0, "ask": 0.0, "volume": 147}, {"strike": 115.0, "lastPrice": 17.17, "bid": 0.0, "ask": 0.0, "volume": 12}, {"strike": 120.0, "lastPrice": 13.4, "bid": 0.0, "ask": 0.0, "volume": 62}, {"strike": 125.0, "lastPrice": 10.6, "bid": 0.0, "ask": 0.0, "volume": 24}, {"strike": 130.0, "lastPrice": 7.9, "bid": 0.0, "ask": 0.0, "volume": 109}, {"strike": 135.0, "lastPrice": 6.08, "bid": 0.0, "ask": 0.0, "volume": 178}, {"strike": 140.0, "lastPrice": 4.25, "bid": 0.0, "ask": 0.0, "volume": 111}, {"strike": 145.0, "lastPrice": 3.0, "bid": 0.0, "ask": 0.0, "volume": 92}, {"strike": 150.0, "lastPrice": 2.04, "bid": 0.0, "ask": 0.0, "volume": 46}, {"strike": 155.0, "lastPrice": 1.44, "bid": 0.0, "ask": 0.0, "volume": 169}, {"strike": 160.0, "lastPrice": 1.1, "bid": 0.0, "ask": 0.0, "volume": 11}], "puts": [{"strike": 45.0, "lastPrice": 0.05, "bid": 0.0, "ask": 0.0, "volume": 1}, {"strike": 47.5, "lastPrice": 0.01, "bid": 0.0, "ask": 0.0, "volume": 8}, {"strike": 50.0, "lastPrice": 0.07, "bid": 0.0, "ask": 2.18, "volume": 201}, {"strike": 55.0, "lastPrice": 0.04, "bid": 0.0, "ask": 0.0, "volume": 8}, {"strike": 60.0, "lastPrice": 0.1, "bid": 0.0, "ask": 0.0, "volume": 2}, {"strike": 65.0, "lastPrice": 0.15, "bid": 0.0, "ask": 0.0, "volume": 2}, {"strike": 70.0, "lastPrice": 0.23, "bid": 0.0, "ask": 0.0, "volume": 281}, {"strike": 75.0, "lastPrice": 0.32, "bid": 0.0, "ask": 0.0, "volume": 1}, {"strike": 77.5, "lastPrice": 0.49, "bid": 0.0, "ask": 0.0, "volume": 1}, {"strike": 80.0, "lastPrice": 0.35, "bid": 0.0, "ask": 0.0, "volume": 2}, {"strike": 82.5, "lastPrice": 0.61, "bid": 0.0, "ask": 0.0, "volume": 5}, {"strike": 85.0, "lastPrice": 0.62, "bid": 0.0, "ask": 0.0, "volume": 1}, {"strike": 87.5, "lastPrice": 0.65, "bid": 0.0, "ask": 0.0, "volume": 12}, {"strike": 90.0, "lastPrice": 0.8, "bid": 0.0, "ask": 0.0, "volume": 18}, {"strike": 92.5, "lastPrice": 0.93, "bid": 0.0, "ask": 0.0, "volume": 6}, {"strike": 95.0, "lastPrice": 1.1, "bid": 0.0, "ask": 0.0, "volume": 1}, {"strike": 97.5, "lastPrice": 1.29, "bid": 0.0, "ask": 0.0, "volume": 31}, {"strike": 100.0, "lastPrice": 1.5, "bid": 0.0, "ask": 0.0, "volume": 331}, {"strike": 105.0, "lastPrice": 2.07, "bid": 0.0, "ask": 0.0, "volume": 208}, {"strike": 110.0, "lastPrice": 2.88, "bid": 0.0, "ask": 0.0, "volume": 50}, {"strike": 115.0, "lastPrice": 4.05, "bid": 0.0, "ask": 0.0, "volume": 117}, {"strike": 120.0, "lastPrice": 5.5, "bid": 0.0, "ask": 0.0, "volume": 185}, {"strike": 125.0, "lastPrice": 7.3, "bid": 0.0, "ask": 0.0, "volume": 203}, {"strike": 130.0, "lastPrice": 9.65, "bid": 0.0, "ask": 0.0, "volume": 83}, {"strike": 135.0, "lastPrice": 12.75, "bid": 0.0, "ask": 0.0, "volume": 1}, {"strike": 140.0, "lastPrice": 15.61, "bid": 0.0, "ask": 0.0, "volume": 1}, {"strike": 145.0, "lastPrice": 18.25, "bid": 0.0, "ask": 0.0, "volume": 1}, {"strike": 150.0, "lastPrice": 46.81, "bid": 46.7, "ask": 49.8, "volume": 4}, {"strike": 155.0, "lastPrice": 27.2, "bid": 0.0, "ask": 0.0, "volume": 6}]}}